<?xml version="1.0" encoding="UTF-8" ?>
<GuitarData>
    <Guitar>
        <Name>Les Paul</Name>
        <Manufacturer>Gibson</Manufacturer>
        <YearIntroduced>1952</YearIntroduced>
        <LargeImageUrl>Les_Paul.jpg</LargeImageUrl>
        <LargeImageWidth>294</LargeImageWidth>
        <LargeImageHeight>480</LargeImageHeight>
        <SmallImageUrl></SmallImageUrl>
        <DetailsURL>https://www.gibson.com/Guitar/CUSQKW566/60th-Anniversary-1960-Les-Paul-Standard/V1-Deep-Cherry-Sunburst</DetailsURL>
    </Guitar>
    <Guitar>
        <Name>Les Paul SG</Name>
        <Manufacturer>Gibson</Manufacturer>
        <YearIntroduced>1961</YearIntroduced>
        <LargeImageUrl>SG_Custom_Standard.jpg</LargeImageUrl>
        <LargeImageWidth>360</LargeImageWidth>
        <LargeImageHeight>480</LargeImageHeight>
        <SmallImageUrl></SmallImageUrl>
        <DetailsURL>https://www.gibson.com/Guitar/CUSGSY394/1963-Les-Paul-SG-Custom-Reissue-w-Maestro-Vibrola/Classic-White</DetailsURL>
    </Guitar>
    <Guitar>
        <Name>ES-335</Name>
        <Manufacturer>Gibson</Manufacturer>
        <YearIntroduced>1958</YearIntroduced>
        <LargeImageUrl>ES-335.jpg</LargeImageUrl>
        <LargeImageWidth>300</LargeImageWidth>
        <LargeImageHeight>480</LargeImageHeight>
        <SmallImageUrl></SmallImageUrl>
        <DetailsURL>https://www.gibson.com/Guitar/CUSKP2119/1959-ES-335-Reissue/Vintage-Burst</DetailsURL>
    </Guitar>
    <Guitar>
        <Name>Stratocaster</Name>
        <Manufacturer>Fender</Manufacturer>
        <YearIntroduced>1954</YearIntroduced>
        <LargeImageUrl>Fender_Stratocaster.jpg</LargeImageUrl>
        <LargeImageWidth>301</LargeImageWidth>
        <LargeImageHeight>480</LargeImageHeight>
        <SmallImageUrl></SmallImageUrl>
        <DetailsURL>https://shop.fender.com/en-US/electric-guitars/stratocaster/tom-morello-stratocaster/0140350706.html</DetailsURL>
    </Guitar>
    <Guitar>
        <Name>Telecaster</Name>
        <Manufacturer>Fender</Manufacturer>
        <YearIntroduced>1950</YearIntroduced>
        <LargeImageUrl>Fender_Telecaster.png</LargeImageUrl>
        <LargeImageWidth>177</LargeImageWidth>
        <LargeImageHeight>480</LargeImageHeight>
        <SmallImageUrl></SmallImageUrl>
        <DetailsURL>https://shop.fender.com/en-US/electric-guitars/telecaster/rarities-red-mahogany-top-telecaster/0176506821.html</DetailsURL>
    </Guitar>
    <Guitar>
        <Name>Jaguar</Name>
        <Manufacturer>Fender</Manufacturer>
        <YearIntroduced>1962</YearIntroduced>
        <LargeImageUrl>Fender_Jaguar.jpg</LargeImageUrl>
        <LargeImageWidth>188</LargeImageWidth>
        <LargeImageHeight>480</LargeImageHeight>
        <SmallImageUrl></SmallImageUrl>
        <DetailsURL>https://shop.fender.com/en-US/electric-guitars/jaguar/kurt-cobain-jaguar-left-hand/0143021700.html</DetailsURL>
    </Guitar>
</GuitarData>
